<?xml version="1.0" encoding="UTF-8"?>

<Document>
    <Hero name="Hawk" transcendence="0" image="../images/SiroccoLoRese461.jpg" />
    <Information>Complications, background and other information</Information>
   <Abilities>
       <Strength value="-2" />
       <Agility value="3" />
       <Fighting value="3" />
       <Awareness value="2" />
       <Stamina value="-2" />
       <Dexterity value="0" />
       <Intellect value="-4" />
       <Presence value="0" />
   </Abilities>
   <Powers>
      <Row name="Flight" text="30 MPH" action="Free" range="Personal" duration="Sustained" rank="4">
          <Modifier name="Other Rank Flaw" applications="1" text="Wings" />
      </Row>
       <Row name="Senses" cost="1" text="Extended Vision" action="None" range="Personal" duration="Permanent" rank="1" />
       <Row name="Senses" cost="1" text="Low-light Vision" action="None" range="Personal" duration="Permanent" rank="1" />
      <Row name="Shrinking" text="-2 strength and -2 stamina included above" action="None" range="Personal" duration="Permanent" rank="2">
          <Modifier name="Permanent" />
          <Modifier name="Innate" />
      </Row>
   </Powers>
    <Equipment></Equipment>
    <Advantages></Advantages>
   <Skills>
       <Row name="Close Combat" subtype="Unarmed" rank="4" ability="Fighting" />
       <Row name="Perception" rank="6" ability="Awareness" />
   </Skills>
   <Defenses>
       <Dodge value="2" />
       <Fortitude value="4" />
       <Parry value="2" />
       <Will value="2" />
   </Defenses>
</Document>
